{
  "creds": {
    "noiseKey": {
      "private": {
        "type": "Buffer",
        "data": "0Nvb7uL5zkkBWHKWbBPgqGYR0hJE+YMK9xwKLYZiwno="
      },
      "public": {
        "type": "Buffer",
        "data": "4vwQ+HN8JcY8RJ2r4z67Zkkfhw3M3vScI98magyfLmA="
      }
    },
    "signedIdentityKey": {
      "private": {
        "type": "Buffer",
        "data": "mF0TLY1ydGuL4dLB8rQU83HAC/ehVgwWUPK6RW53lW0="
      },
      "public": {
        "type": "Buffer",
        "data": "GMx54izk1+PN49dYrQSXdjpSx78diDzFRoEVWhn4PRo="
      }
    },
    "signedPreKey": {
      "keyPair": {
        "private": {
          "type": "Buffer",
          "data": "iCEDp1lA4EYuUU3vaxYvqOhl0dYqeVW/18UYTRANn3A="
        },
        "public": {
          "type": "Buffer",
          "data": "hwcQ0Kv0RabfKy8G5k5h4DuwMzwmaqUMTrBTggZLTH8="
        }
      },
      "signature": {
        "type": "Buffer",
        "data": "yIuoNFkB2vhE5bevVRnNPabKT7NNIXIETaYZokZUhkMDuoHfsLiqTmmCsgTpbaKy1b5IS5wvTg4LcImTQbrRjA=="
      },
      "keyId": 1
    },
    "registrationId": 175,
    "advSecretKey": "hZJf+wjf0eHXgqtSyriiFYtRsKBaBLuon1eFH7ciQyk=",
    "processedHistoryMessages": [
      {
        "key": {
          "remoteJid": "6285691240122@s.whatsapp.net",
          "fromMe": true,
          "id": "1B127AF6E6189C28C0F190605C455F88"
        },
        "messageTimestamp": 1667262897
      },
      {
        "key": {
          "remoteJid": "6285691240122@s.whatsapp.net",
          "fromMe": true,
          "id": "58B87018B5C15FB629554D76698E7814"
        },
        "messageTimestamp": 1667262898
      },
      {
        "key": {
          "remoteJid": "6285691240122@s.whatsapp.net",
          "fromMe": true,
          "id": "2F26A3AEF5A02FB745AB525BF073BC83"
        },
        "messageTimestamp": 1667262914
      }
    ],
    "nextPreKeyId": 31,
    "firstUnuploadedPreKeyId": 31,
    "accountSettings": {
      "unarchiveChats": false
    },
    "account": {
      "details": "CN6gqM4GEKrTgZsGGAE=",
      "accountSignatureKey": "zOWepfGtFYRxetaBqKwseHsbkqpwj+HAjWpvqn0sBzw=",
      "accountSignature": "d8aNIQKzfr0OEEyJThPAsyy3q9asYAK+hYW8f2rWSXpMgxA2OiiIdDsI3wxkW9pIJApMcCh55te4yA0m5+ypAA==",
      "deviceSignature": "bEwrtrfhZOx90E6+MNDxQAXHvSofLsrrIJIi5SwTdEKj0CzBrZf9Kigiff3/EIbL1hUYfMu3uXHeYjtKHImujA=="
    },
    "me": {
      "id": "6285691240122:27@s.whatsapp.net",
      "name": "Filho Maker"
    },
    "signalIdentities": [
      {
        "identifier": {
          "name": "6285691240122:27@s.whatsapp.net",
          "deviceId": 0
        },
        "identifierKey": {
          "type": "Buffer",
          "data": "BczlnqXxrRWEcXrWgaisLHh7G5KqcI/hwI1qb6p9LAc8"
        }
      }
    ],
    "platform": "android",
    "lastAccountSyncTimestamp": 1667262893,
    "myAppStateKeyId": "AAAAADdF"
  },
  "keys": {
    "preKeys": {
      "1": {
        "private": {
          "type": "Buffer",
          "data": "KKuilrsS2litJO3+5e52LsV6sZlhujWt2s5st2gVZFk="
        },
        "public": {
          "type": "Buffer",
          "data": "xVJR87MUAaibsTBz42i9HnlTeR169ks5aLgz0/JX4TY="
        }
      },
      "2": {
        "private": {
          "type": "Buffer",
          "data": "6ETGrvX3IMt6jFPqAix9qrfVJp9Hr73wWuQEOIvB3lU="
        },
        "public": {
          "type": "Buffer",
          "data": "ps/TGEgFV8L2EaUBZdwj+vNQiLfPOyTvkNKHwBi97jQ="
        }
      },
      "3": {
        "private": {
          "type": "Buffer",
          "data": "iEw+A8qq8/1vZ15QWaFvnbyi4EzikkOfm2ijlC5uDEI="
        },
        "public": {
          "type": "Buffer",
          "data": "xp3IIuM0l34Qy+A/+8HNb97h0ypFwFuczZrRMhLjUBA="
        }
      },
      "4": {
        "private": {
          "type": "Buffer",
          "data": "wKJ4QIsryTpGY6hA5ZFUaLeUjznW39PTC/8yhn792lg="
        },
        "public": {
          "type": "Buffer",
          "data": "wPNzrLtyCWuj+xRZcW+QfL6Fi+DQhV6NkPe+v8mnBjg="
        }
      },
      "5": {
        "private": {
          "type": "Buffer",
          "data": "uNbjpcYW2KVvW9s3NKIY4vYSshuarc1dYa0yfws8nkA="
        },
        "public": {
          "type": "Buffer",
          "data": "DoWshJKj1RTSW3X9pagOrBfMDLjb9XoAUZcIHdcwrFA="
        }
      },
      "6": {
        "private": {
          "type": "Buffer",
          "data": "UGLI7YAADBceVbPEnj9+BUFvSCTeMEIt80fjWp8BLmE="
        },
        "public": {
          "type": "Buffer",
          "data": "s/IvpxDJGR2Oh7RRoqADe2uBApi+XUqEPvKtJo3Uyic="
        }
      },
      "7": {
        "private": {
          "type": "Buffer",
          "data": "+ILDBmjeNg9hqfmfXP9ymP3NpdvKhiMiHbhfuK8D2Wk="
        },
        "public": {
          "type": "Buffer",
          "data": "IIxkJoF9AydfGgdpQ3/+uBufBmEkC/ezih5UohANvVQ="
        }
      },
      "8": {
        "private": {
          "type": "Buffer",
          "data": "kKt9gnQBDHJdDCfWbFQux7l+gOrqQxlcdtSiY1LTqEA="
        },
        "public": {
          "type": "Buffer",
          "data": "E2HEkLoUSVgSs+8SNjDJBfvXJ47m6lRZsgHHCq26MC8="
        }
      },
      "9": {
        "private": {
          "type": "Buffer",
          "data": "GKeiznxoWnzpN1wMV3NbcyCDOIoOrEnqTXg4w/z36lA="
        },
        "public": {
          "type": "Buffer",
          "data": "nOZi2PaCDUwd1UXhFLUo6tVu8ezXg3GRNriEmXcxsCI="
        }
      },
      "10": {
        "private": {
          "type": "Buffer",
          "data": "EOD6L6IQh2VdqLO4wGRE4osgX6vdZvcB80gUgDXSCUE="
        },
        "public": {
          "type": "Buffer",
          "data": "VmrNyiSbZ/dcHiecaatpiO8TJHLWZqQOjdh0M4ZfXA0="
        }
      },
      "11": {
        "private": {
          "type": "Buffer",
          "data": "MF0QFTKn1VcTHdDZ+D7XNuMD+ksYTljp6I/J1CuZiF4="
        },
        "public": {
          "type": "Buffer",
          "data": "GMK4TSyikvazvhC45Ht6I/Ls8LzPWTTQiXSV+NNK2mU="
        }
      },
      "12": {
        "private": {
          "type": "Buffer",
          "data": "uOFHClx1W/BXxT+yuURTXYFnMVpAmNpqWtFSaT59GHE="
        },
        "public": {
          "type": "Buffer",
          "data": "A+Z9M3txTfgs7Oab8aFa2dwbiTAsKXubTtqOc4lUOXA="
        }
      },
      "13": {
        "private": {
          "type": "Buffer",
          "data": "iKKtC7JVqtZZGOGctw5s78j5hQM31jAABg5V1p4h2Gw="
        },
        "public": {
          "type": "Buffer",
          "data": "soqFufFz82jfuwvYrDlvOezLh1UwP+vXdeE+Qzg0HWY="
        }
      },
      "14": {
        "private": {
          "type": "Buffer",
          "data": "MEb5xPCMvQSSqhzwtui/Kc4kHJkjQAM+yHWg9S98Kl0="
        },
        "public": {
          "type": "Buffer",
          "data": "Z5B8NFuDOemQKV+dggtWABtj/D3J7qkxhFTEnhYrOCM="
        }
      },
      "15": {
        "private": {
          "type": "Buffer",
          "data": "0MbAKNY6eQPgu19aBn8iDFPi+JzTHYX1uGDaNiCbzkc="
        },
        "public": {
          "type": "Buffer",
          "data": "jyF0flkEt3mobDrD6PmipEDsGljyP73ntoR8ZI5a8x4="
        }
      },
      "16": {
        "private": {
          "type": "Buffer",
          "data": "qIi79dPCkFP+oMDP7CzsdrcaKH92XWijI7Y/NgDsyWY="
        },
        "public": {
          "type": "Buffer",
          "data": "67ykg9Ljt78ukpAvDGJAk/2BqK4xJDLHdcCWc2ik8BE="
        }
      },
      "17": {
        "private": {
          "type": "Buffer",
          "data": "GFopOT70Werw26iy8ZkbzwlX8QNpGI83TAxmFbta7Uw="
        },
        "public": {
          "type": "Buffer",
          "data": "21yMJLlSdSAHZedim+nv7xpmtWyunECF47D2Vrf0Mls="
        }
      },
      "18": {
        "private": {
          "type": "Buffer",
          "data": "UJVrT2S7AceUfHWX89J5n4OxiB4TpnWG2QFBtNJjpX4="
        },
        "public": {
          "type": "Buffer",
          "data": "cYl+AzTWx2Tg6OZa4LesjkxG5d3dJUSp0BGR5d4iujo="
        }
      },
      "19": null,
      "20": {
        "private": {
          "type": "Buffer",
          "data": "mASQgABtP62r/a+CFBlNK/nRgklCf8MhnxoUKYB1IXk="
        },
        "public": {
          "type": "Buffer",
          "data": "oSO7+63Dxs6B3cgobEge/eHpbnzHRrKK4pkqnUA5ikE="
        }
      },
      "21": {
        "private": {
          "type": "Buffer",
          "data": "6DTMUNWRAfZV4/bsEqPAPMmk7aKtv/JMrtYMzt3ZS2s="
        },
        "public": {
          "type": "Buffer",
          "data": "HsxkB3VZr81AOP1f20nz6Xkd74r3zHiQt9Xi1HV25S0="
        }
      },
      "22": {
        "private": {
          "type": "Buffer",
          "data": "qOeMHEhgp/Lue2CWp6l6+TMQH08uDwk/SK0puj1nSFQ="
        },
        "public": {
          "type": "Buffer",
          "data": "FhXh7QbqYWkX+pkg2OZHUPEyvE2o9iEUHB7CkOCY0AM="
        }
      },
      "23": {
        "private": {
          "type": "Buffer",
          "data": "aNN37tm1HDdOLUycS1OFjKk54o//OruGjdZOYsFaLEo="
        },
        "public": {
          "type": "Buffer",
          "data": "kPhWxyE5XQRKcocxqzvDUafTYb3XZnw3ITAHyQ/2sgA="
        }
      },
      "24": {
        "private": {
          "type": "Buffer",
          "data": "WMhqhS9LYmUtZmRDd7MIvMY1RR/BtyjYIPrZoa1AcFE="
        },
        "public": {
          "type": "Buffer",
          "data": "g8WoQ+NnJ5DBe6c/UURG+zsGIB1o92OvWWcEsX9f5GU="
        }
      },
      "25": {
        "private": {
          "type": "Buffer",
          "data": "QMLSI8NKzbz9EB4GrKnxuCbA3fxVhXSQB7guLCMQGGs="
        },
        "public": {
          "type": "Buffer",
          "data": "CWchTgSDCVGI91Bhx79bbgyjUc61rIVlrYE90OBvTio="
        }
      },
      "26": {
        "private": {
          "type": "Buffer",
          "data": "+LvObK/e+A12RhbJO7kV4r/AYfVxHypUyWskd0qe93M="
        },
        "public": {
          "type": "Buffer",
          "data": "HFXq5iP3mIEC04rHfklMstik7B6oahX/820gOQdYCyE="
        }
      },
      "27": {
        "private": {
          "type": "Buffer",
          "data": "8Dpc0M7+QgFe6Wuoo+/JmaGc9UIv3etNwxNGGHcTm0M="
        },
        "public": {
          "type": "Buffer",
          "data": "26SitexIkk/u+gQXhAZZpjAFTnJxqD97427pNUgCjnA="
        }
      },
      "28": {
        "private": {
          "type": "Buffer",
          "data": "oH2Y2vtUJoBPE4RZNyEkyMefxZ8/RPHIqrbhHHBESEU="
        },
        "public": {
          "type": "Buffer",
          "data": "NNdkVAkOK5yH2CxatifcKddNPHMDL+p3I88A1wvCYBA="
        }
      },
      "29": {
        "private": {
          "type": "Buffer",
          "data": "gPNdd0f/7aJ51Ofpm67GPu7U8C20lBtRe6fExsF2l2o="
        },
        "public": {
          "type": "Buffer",
          "data": "0TZInARz8dhChuDWynG2xpRnAj0IN1NJnGkulHLVZ3E="
        }
      },
      "30": {
        "private": {
          "type": "Buffer",
          "data": "QD4oCQR4i+sDEoWGPb430CBjtedrK8dD+ZMZPeZkwlM="
        },
        "public": {
          "type": "Buffer",
          "data": "Mh3st1/PKlSM/Vxmh4uhl2Cwx6YgAQ1WCOLjc/otkjs="
        }
      }
    },
    "sessions": {
      "6285691240122.0": {
        "_sessions": {
          "BRYAMYLKr+mCbjilMCzpL6gzVTU0UKX/r+63aeKVVV8f": {
            "registrationId": 536666679,
            "currentRatchet": {
              "ephemeralKeyPair": {
                "pubKey": "BWIqzakxdChw1Svo9YcX3/zXL/zqcPJJXEKyXzwHahks",
                "privKey": "mK10sato+2zfYPwX/I1LCqIpKwhcVf9ems5wz/LDcls="
              },
              "lastRemoteEphemeralKey": "BefrSh/hTO3kx72FFxLe4o8dUaqEY5NAupAURIRXdvtK",
              "previousCounter": 0,
              "rootKey": "IlUDnCyiDdbiorKJhMLIEs2D/5mCa4rjjujZ6QzC1L0="
            },
            "indexInfo": {
              "baseKey": "BRYAMYLKr+mCbjilMCzpL6gzVTU0UKX/r+63aeKVVV8f",
              "baseKeyType": 2,
              "closed": -1,
              "used": 1667262926221,
              "created": 1667262894613,
              "remoteIdentityKey": "BczlnqXxrRWEcXrWgaisLHh7G5KqcI/hwI1qb6p9LAc8"
            },
            "_chains": {
              "BZU9DA6+QK3fsWXhhMgQNaQD/salCeLpXupuOpDzGggY": {
                "chainKey": {
                  "counter": 7
                },
                "chainType": 2,
                "messageKeys": {}
              },
              "BR6ALm+YaJd9Zd7bfZ7DQBs7J/bpw9Vuxu7SaEYF2ZlU": {
                "chainKey": {
                  "counter": 0
                },
                "chainType": 2,
                "messageKeys": {}
              },
              "BefrSh/hTO3kx72FFxLe4o8dUaqEY5NAupAURIRXdvtK": {
                "chainKey": {
                  "counter": 0,
                  "key": "3mnwsji5DC4ciR4G2ENKJxbX3Di2v8r+EjWbtnJocso="
                },
                "chainType": 2,
                "messageKeys": {}
              },
              "BWIqzakxdChw1Svo9YcX3/zXL/zqcPJJXEKyXzwHahks": {
                "chainKey": {
                  "counter": 2,
                  "key": "SRwR+LMCvSqd7mip92Hjkp1l9LAU2+syImruMo5g0MU="
                },
                "chainType": 1,
                "messageKeys": {}
              }
            }
          }
        },
        "version": "v1"
      },
      "6281399029499.0": {
        "_sessions": {
          "BWDLWuAdPax8VOn9MgKzQ0hdazTiW0PBBof8qG9TZ39B": {
            "registrationId": 1567914481,
            "currentRatchet": {
              "ephemeralKeyPair": {
                "pubKey": "Be2nO302RJJuUibSD/YZJ8ZnFc4GGx3SBTn/xXG8C0M6",
                "privKey": "WBXy406r3ndIb5CQCEP+FV9B37X8JYtyF363RaIcflY="
              },
              "lastRemoteEphemeralKey": "Baq7HYLcL4wu6xcM/IjNW16cMqS50a9tXNvj2FZYLzR3",
              "previousCounter": 0,
              "rootKey": "URrCbX/c4VFIpGHElqf5PNbPMnNO8FwAxcA+rzYlmb0="
            },
            "indexInfo": {
              "baseKey": "BWDLWuAdPax8VOn9MgKzQ0hdazTiW0PBBof8qG9TZ39B",
              "baseKeyType": 1,
              "closed": -1,
              "used": 1667262917465,
              "created": 1667262917465,
              "remoteIdentityKey": "Bc9GL7rU2ziX4gVJ1Mi8eCv81kC9D5FYVMBwTsak/B0U"
            },
            "_chains": {
              "Be2nO302RJJuUibSD/YZJ8ZnFc4GGx3SBTn/xXG8C0M6": {
                "chainKey": {
                  "counter": 4,
                  "key": "/ad4JwuARkCAQpTxDVu8EOD66CJMZfAhOCVl+9uEIxU="
                },
                "chainType": 1,
                "messageKeys": {}
              }
            },
            "pendingPreKey": {
              "signedKeyId": 0,
              "baseKey": "BWDLWuAdPax8VOn9MgKzQ0hdazTiW0PBBof8qG9TZ39B",
              "preKeyId": 11295347
            }
          }
        },
        "version": "v1"
      }
    },
    "appStateSyncKeys": {
      "AAAAADdF": {
        "keyData": "yD83lW67qXKyiAy5swglF0MvUJZLZTY0gfhpm1adWjQ=",
        "fingerprint": {
          "rawId": 1774850142,
          "currentIndex": 1,
          "deviceIndexes": [
            0,
            1
          ]
        },
        "timestamp": "1667262895912"
      }
    },
    "appStateVersions": {
      "critical_block": {
        "version": 1,
        "hash": {
          "type": "Buffer",
          "data": "UWkg58Y2au8qv+ZDFQrZUdTCK3ZRKSLDVI+8OhUGCnVts1r+cNR1qvavx3NvfbuJEJrU40fl1YVmjoKH34+o6cWab2pv7JzArCR2lkM74rbVEWzirLsq9vuMClZ7XSq+ITuZi7tW26qIjdSUMZZ9Dlo1LaOj7fXSpL2cPvvLPD8="
        },
        "indexValueMap": {
          "+ocV59NynW3y1aQ9q4Sj1qgZR9F2uvW4URhkn6Tbg4Y=": {
            "valueMac": {
              "type": "Buffer",
              "data": "eQty7ALk8uewu5FQ9eggXPf/QUSbfSXuqrHkG5tV3Vc="
            }
          },
          "UXpJKlYbcNp5JZ/g/OuJiLyPTJ7FvCGA/O3nPuGddvM=": {
            "valueMac": {
              "type": "Buffer",
              "data": "pJXP/2QnQfMTUYD2tzqH8Gi3wTTQt7V4m6/cdqBfQKw="
            }
          }
        }
      },
      "regular": {
        "version": 1,
        "hash": {
          "type": "Buffer",
          "data": "AENjVMOHIk8Q1IhvqX3ksAqzNvURK5GpSqRLJ0UUCv2tmpqRYnDkwj6XGsVNghlSf9W+YtBACI/1PAdtDzM5BxxIz9lhG+7BB8CESJExyDVpnmFCkShpBT7ZvqHZCnc1Udu7LI1S1WZcUdIVao/SK3xglSXNuYL/C/swpDJ4VhE="
        },
        "indexValueMap": {
          "tI8kbSvy4wazkmCliE84hG/WSc00YmXfz5rqMDwmApQ=": {
            "valueMac": {
              "type": "Buffer",
              "data": "8HgRP2AFNPCJjgvhHsG93sVp0xKMML/QIGV45++UQWM="
            }
          }
        }
      },
      "critical_unblock_low": {
        "version": 1,
        "hash": {
          "type": "Buffer",
          "data": "PRwVJKM9FdWVY3WMyM+k/yqwkJmAXdOsNd4/mKqEO/gA/rjjTpwzWm83kuJ0UNXu0CssnWV2lB/yHQsj2T+ib3ZDD38MXIkHpnmCakckIYuON+vYVpqhXCScLwrdKdWuFQttb4daeVA77BJmoTACwHd44jJrGV+AQyt251hgVqE="
        },
        "indexValueMap": {
          "7GC36IAF7jin7GqxZxFxFlrO8g9Qn4kkCJrAqXq4Jdc=": {
            "valueMac": {
              "type": "Buffer",
              "data": "I6ZSHEEV4zs0gmeiT9sZPk9zpVo6Hj3bjUJHj4n3vHo="
            }
          },
          "092wJea2ExnR8m5namVXFVSVMMipcsyPYorR7hazl0g=": {
            "valueMac": {
              "type": "Buffer",
              "data": "HRj4RvAJfjz7iMBg44cX+KBnX2yzyZ7XsZLvDy8GqVE="
            }
          },
          "pNVsI1QPW/jqRcn6ddAQuuq+B6lVkhm4752cuvezymE=": {
            "valueMac": {
              "type": "Buffer",
              "data": "NY5SCGudlyxmcoC4oR+vZFxo/VfzoNfPyJ3PqzGqXAs="
            }
          },
          "9cS9AHdRTzI1nM7eZ6lO1SzF3pSEIsrHS4lrVjOVFXk=": {
            "valueMac": {
              "type": "Buffer",
              "data": "CxUT9A4QVNhUoKOWhZKph0MoUq35ioNaVz0F9Xb8S4A="
            }
          },
          "HTAryDSlx0mmpavYv+mpshWlIEu6MrEr30pACWojWUw=": {
            "valueMac": {
              "type": "Buffer",
              "data": "LDJJr9HlFcfKRBXix7t1VSxmiNB6oyPhcuUkZYpsIm4="
            }
          },
          "uYHWbCPR+oDlNjK/oJ38ecSJB5VJlJnnPjxnGnIpp3s=": {
            "valueMac": {
              "type": "Buffer",
              "data": "wEkhGYzNxumlL7MNzoyALEhxT+XJzrtqqBYE0UhZoFs="
            }
          },
          "x0Vl9+lodaysCv6ULTBNH/4pLz7R6gX1J1pAFtHCxIY=": {
            "valueMac": {
              "type": "Buffer",
              "data": "0xbNVXGtp/laamLM2sLLHF1KB+rO5rJwGtEiinxDihw="
            }
          },
          "lbxxuwM06Q5879YfTBhFu5PydKbMKpeKSKjxIIbq8Mk=": {
            "valueMac": {
              "type": "Buffer",
              "data": "wXZwM3/Dd7zBhgxyWpJAzNi9afC4799v/EHjvCOtm7s="
            }
          },
          "JDMVPgf0E2OUB1dootUxa4cItZ49Tk0wVwzJhIdEHeU=": {
            "valueMac": {
              "type": "Buffer",
              "data": "Bal8Xs4W1mHw7EHzHqB7n3xwAIHhjjsueS0CSJhAAzU="
            }
          },
          "RzdFRHof3cET8AiFiVKdXddQGsyHWYi87pNXrK2xCzw=": {
            "valueMac": {
              "type": "Buffer",
              "data": "WgIKpaqzQUZBPVwkqTh5UrCiy09XBrr/iIqpwOOlp7c="
            }
          },
          "nZ0GKf8jF8bySURKIGUTBRzHHjva8IJ2ylpA1umnTpk=": {
            "valueMac": {
              "type": "Buffer",
              "data": "8aiGPjXwk4VmjkneFZe2nzUSjrZRTBt/4tB8cvvpo/w="
            }
          },
          "qvymzX0zM+APb6wAupvD2D9mT7W7zmu4fNq7fPpoPc0=": {
            "valueMac": {
              "type": "Buffer",
              "data": "TM9ANtfsGkOKqOTFOQYT48S4gUG4mwpKfVrMPiJRNXo="
            }
          },
          "KvTfs4qoWMpFZJ344P1bC4SIRGL+YD5keeJZfMku4xY=": {
            "valueMac": {
              "type": "Buffer",
              "data": "mFQuo+0bzYj2SHLw42HKSrXx08yMCop0Zb103ZRNrl0="
            }
          },
          "vTcoqUxTZ8TrGSOKDJeVDnt7G7VG6MzCaKb1IO9fWW4=": {
            "valueMac": {
              "type": "Buffer",
              "data": "WSPoxjX+zxRL3COSrkKSQM04ZlwLwTbPPCnLMBvOLxU="
            }
          },
          "o9NasikICZPSUFWkI6G50T4oNVWk/orIut/603te3/c=": {
            "valueMac": {
              "type": "Buffer",
              "data": "/OlvNiGK1xatiII7p4BfOKI2Qd/bAcoPcchzxWA1LHE="
            }
          },
          "JR45cJ376cV42o4uetovW3ohkhh/vXEWYzNiOFwJGg0=": {
            "valueMac": {
              "type": "Buffer",
              "data": "fbpxWawuZ3OCxd0Hw51Hl4SzZLwcgx/FBTT+YWyvbOA="
            }
          },
          "LV/sUE5Y7kbQpc44SZ+OJhib0JkiptLE2l7rNKaFcD0=": {
            "valueMac": {
              "type": "Buffer",
              "data": "Day8vhvWBPiU2fHkx+sYtDjnBmGhEjir/MGZS06wCn8="
            }
          },
          "/8Y9tr/Bb8qxMKVbjwrmVqL/YqIMVHLIy+2bujOeVQQ=": {
            "valueMac": {
              "type": "Buffer",
              "data": "4UuXmmHyLtj88LCMSD0qyoLm9IniVlK2i96iAcO2j+g="
            }
          },
          "JjgN+ozouF66SlJ1nMQsshXW1Nt76b3BHsC9ObUvmDo=": {
            "valueMac": {
              "type": "Buffer",
              "data": "uoSyDU8AiMk0GeCuEBUXP5L+p8FE0/gC97vt9hYx7pA="
            }
          },
          "JvFRyb/8Dfnw7YTiCtnXQsksjISYeq49i6IiE8a8FiI=": {
            "valueMac": {
              "type": "Buffer",
              "data": "FRpUCv0qPAxVML8bGbTvI+gSPeAR6cTAGHRpqDdrO4Y="
            }
          },
          "D89HZ72ff12IJh5d/TsmvUvLpcfrd70KowJvKwiyXLM=": {
            "valueMac": {
              "type": "Buffer",
              "data": "PZBaDn9vhDh5trJIPHmF/k9qgqIrhAmfoYjXl+gEkbw="
            }
          },
          "io0jrppFpJgjHTklydE2+VAw1wKWnf2kLMycOOA80OI=": {
            "valueMac": {
              "type": "Buffer",
              "data": "Uwmdvy705+rvhGwhUVQWkXFWRow0+rkSkivtItqbmjw="
            }
          },
          "C31K/GEy1mSImhdUVWNLfsageuBG9JoSzqED9JYCs9o=": {
            "valueMac": {
              "type": "Buffer",
              "data": "nvNp8//lfBRCt1Xmd8xyPQU+Tb1LcKorFVtmuQ5I/mc="
            }
          },
          "z89bF0eOS4Okr/AU54JzQG0eldEKAapD6HaunGuXcdw=": {
            "valueMac": {
              "type": "Buffer",
              "data": "tIamueV5H9XVXd387abZ3umVnPO5qVqr+x/or9qAHnU="
            }
          },
          "cOXLngUUsaKBVo5AzMee7o98liVNtzgvOgBtdaO5g9Y=": {
            "valueMac": {
              "type": "Buffer",
              "data": "8KnVS1WRts0ezz+4WcBdRu034sNKr/CluSTVjW2un5o="
            }
          },
          "W9GeQqG1PlB1wp3nuc6gU3ZUMKuF8SadtJWhVthcRUQ=": {
            "valueMac": {
              "type": "Buffer",
              "data": "b9A/CXCwHjy9P1na5zQQzuteWRw1n/XhLnWl7W/qtkA="
            }
          },
          "YbGAKaOuN+MDzHPQs8rQyzNaRGJX5l599nLbx4PcWzE=": {
            "valueMac": {
              "type": "Buffer",
              "data": "zVBLU1HyYYbebpZh3/o067ISkhgg0nCPevCodeLt/go="
            }
          },
          "KZkeNRv/2kucLe+yh00pO4dkXhqnKPNciryMWFIENfk=": {
            "valueMac": {
              "type": "Buffer",
              "data": "tsBrRJnQyxY+oh7g2BzbzMIr5Rz3i9xdLSSrGtt547w="
            }
          },
          "DPvDUDd/ss2nJfb8jDIDgfBizwklFmnPurjgLuP5j58=": {
            "valueMac": {
              "type": "Buffer",
              "data": "5WYrpZckkwhjiv4Rm4pjcyUzXZ5mgCxtmudUvMSUVFM="
            }
          },
          "QvepmTE41aFSLoz7W1oVwOn2ZK6uhebsrt4gsc4A4Ls=": {
            "valueMac": {
              "type": "Buffer",
              "data": "7QBRY4IMgm7LsbC/Jnrd6uEQLXcmhpyQgbPz++hZdXg="
            }
          },
          "pu4EGF587aG+4tF7vdb1WBdk1AImC3Yv7bYScZprWVg=": {
            "valueMac": {
              "type": "Buffer",
              "data": "mCkwAeXXDLwkmPd5HUg1QgQ1uSRjsWFpWldmhCKjEeo="
            }
          },
          "HmJF+hh+3HtZ5l/Gb3zNLH1IQvX4yI9ueV55TDFjXrs=": {
            "valueMac": {
              "type": "Buffer",
              "data": "LTfBL94WWBDLQjYnO2ogjWKRFXEp18wOyu1GEc43/1s="
            }
          },
          "gd6MGhapQ5XuNqVUMKd3gJXqpetRGr0XPcwv2DirbsM=": {
            "valueMac": {
              "type": "Buffer",
              "data": "gPiiCEukZF4C+U6CfMcoxDQXN1OLLYOe4Bk+yCsSrPU="
            }
          },
          "yATRofjw3gjTCJY1zyxAl6DgSsLMU8AyhdXkWZN4Vzg=": {
            "valueMac": {
              "type": "Buffer",
              "data": "gkq2WHsTGxsxWfMwTe3ujcwThBGbaZ6txRG2A8mONM4="
            }
          },
          "SMuHVXgtU5Z6VeCI3pBuRXNc9+oV4VIucyh8iwASK/4=": {
            "valueMac": {
              "type": "Buffer",
              "data": "sxu7A0vwnU3QTd/Fo7NFQaAVKrA4owCl1NNOx62Rup0="
            }
          },
          "/M+1yFRvjD7e8G6Yh/WX0Pk6nUq+bzuY1hiBwnF95wI=": {
            "valueMac": {
              "type": "Buffer",
              "data": "/c4wf5jy1OaVUWTPWuiH6rhpmlmNSEUQzJeHrXDBUps="
            }
          },
          "FKNE4BLh+iwlv/RUMIvcoZi2eaNk8KfGQlKxorCIkP4=": {
            "valueMac": {
              "type": "Buffer",
              "data": "p33c0Urfcxdi0wQZJl+3onIWJogcBVHJLWOAvVNHHs8="
            }
          },
          "SZQDn22mYnKtO+XohZ6wlXwV0Aa2kiayCDuzZSWvBog=": {
            "valueMac": {
              "type": "Buffer",
              "data": "UlfqiMomTstpQ+71MhFXEa6+1WdWkAvx4NB/5sed0KI="
            }
          },
          "g210aRFnYb4vyP8YLxylNfOcJcI3/eRh2fyBgQWxVns=": {
            "valueMac": {
              "type": "Buffer",
              "data": "KrD08HtUP6PxdneyZB+c8Xei5i5PVanSXRcNvbRo050="
            }
          },
          "6i6smRsqV0VsmFhQL5rIDI70xbAmUgkimhtxuVOASiM=": {
            "valueMac": {
              "type": "Buffer",
              "data": "oA3S3ZZRiFhrDC46BfqQYTOwbhzSJKX/j+HplN9RjGM="
            }
          },
          "qN9pJAGws+casiJ+oFdGMIrli/45CF5/20SyqgrQY84=": {
            "valueMac": {
              "type": "Buffer",
              "data": "XetxU8nA7Q2mDPmffcG+w9JMd7kfrqvMopLQP81c+/Y="
            }
          },
          "0IsjkOraaHHb7d+YYisQBsKYriItExYtkpqXIx5Eoog=": {
            "valueMac": {
              "type": "Buffer",
              "data": "Mgv74Dy964o2PtoCFABTiW3YyJI01yLWEZ9Znn6LbFs="
            }
          },
          "4X/bwsG8h5GqqKNzsoN+yBUkjmCGBNCKkGu9WtlnUqg=": {
            "valueMac": {
              "type": "Buffer",
              "data": "Zo2ayGS2++q5Xthi0BJBVYor1rWGYP7IyUWFgw71z8s="
            }
          },
          "kLmmf/02/ZkeZeXS9zk6xKT8mAPS5J2DD5K/WYk4DdE=": {
            "valueMac": {
              "type": "Buffer",
              "data": "C9UNdbUZD7vJu2CqMu3kvdprZdz2dt62OdnTm+4jHdU="
            }
          },
          "jnYwSP4coQBYHNUtJlGMJojWUt3DEoS8aSnFfloRaG8=": {
            "valueMac": {
              "type": "Buffer",
              "data": "xEgMHw+sWiAuTWLt1TB9GECHmN4IKXjgWFsvGYYBKF4="
            }
          },
          "YoZSUo8qXASo18Le/QwLHlmEa/JWptSYgFgc+PCU+BU=": {
            "valueMac": {
              "type": "Buffer",
              "data": "jrAS9NJp5uPxCACJ9wW3WgRTtw/0wBMyPHfuzTD2uoc="
            }
          },
          "v+L0F+ulcrFomrTCs+KW2E/aL1tA9bOvSUd4yOPQSKw=": {
            "valueMac": {
              "type": "Buffer",
              "data": "/01EGGOwXPVLl/jXk98PTQyz+bZuj8F6TWZXBdzf2iM="
            }
          },
          "lJu02fhCjVjay7IFP0BQpG97FUnAqyfBboGcjz2smBk=": {
            "valueMac": {
              "type": "Buffer",
              "data": "eADaF8mgUVtq5is5MnxnBUSCpoOMOMSgmxXXILoSv20="
            }
          },
          "c6547vs8r0V5gF3YyLdX4YiYZI0ROyu5eWlIR3l60PI=": {
            "valueMac": {
              "type": "Buffer",
              "data": "Ds5oytIQrfsWeigXnTXOKL8UwC8qLsc1KQGf+uVFWg4="
            }
          },
          "KXV10j62O9hXB7LVv/ZiEita4ZImqVZEQAO2+Gqc3H4=": {
            "valueMac": {
              "type": "Buffer",
              "data": "TSROEKSGClYuHIkfwBdYlGS6pfnKiyeMprseQtUDOvY="
            }
          },
          "yDKUWD7niuXXi9YsHySsRTUiT4zSSOIL3RzWOcyQrJs=": {
            "valueMac": {
              "type": "Buffer",
              "data": "yd0/jQyTEfvLhxNRac+pEsOSrL699ITN5vfYmSGXuw4="
            }
          },
          "CnyOJWp1QqnkB//W1DYPklCWnlPfyA7jiLvv54KWRxU=": {
            "valueMac": {
              "type": "Buffer",
              "data": "8wifd2v2CSRugebq9FcowRKA52axCMQ4rmeOXsDFWLw="
            }
          },
          "bIFI8BVEULNI1cmzzoB+1gQ2JFh44YDp+4fAUVagnTQ=": {
            "valueMac": {
              "type": "Buffer",
              "data": "4Yc/fB5KQPoPSgFCvspWeBEIouj2R9AfXot+jTydJvQ="
            }
          },
          "+phIJS2NiEwxgjG0BOE3uEBBForXh59XxQEtLpe42Lc=": {
            "valueMac": {
              "type": "Buffer",
              "data": "mdR4eaCxBYVXdXSy1jYhwXrmh7EvvknPN6OgiMCQWVU="
            }
          },
          "u2e0XzHrjmp9WTCWwOoJJFRJGJM2ll5FlMSmwdqsHOY=": {
            "valueMac": {
              "type": "Buffer",
              "data": "Pun6OiDuL5XW4aws9PmgSUgeAVb5+oBA6MOq9EaOzgA="
            }
          },
          "BmR4ESBxWcQTUVkcz/UXSSD8em/mKgB0lVNHY4KOhu0=": {
            "valueMac": {
              "type": "Buffer",
              "data": "6T3ASuO4tB4IOK0IUdHbwduyLwMWDfJGoiIVrq5r444="
            }
          },
          "55HGwNNnch7bTNWBAb2tudlDRqmeMw3XSSu3qgTjEVQ=": {
            "valueMac": {
              "type": "Buffer",
              "data": "adp0MLJUZmovnwbqRaplUbPD3AUsXliPcGb4kPHnzuE="
            }
          },
          "wtFtzSGmczXTRlp/CwKVExMyD/j0YgHsWCayZCXUbWY=": {
            "valueMac": {
              "type": "Buffer",
              "data": "FVeL8O5vwwRuGRQ2QJ7EkJFYBbeDkDCkBqpopxRxHcc="
            }
          },
          "0ECXqqCQvV/86PKj5EE+WetME7A/koXdKjCjgbPh9aY=": {
            "valueMac": {
              "type": "Buffer",
              "data": "1p/dOBAUWm2rP19xTuHrMyRO4L7oiHQpxC2QhrDBFfc="
            }
          },
          "qvKPwQOk1Ets01/9lrlSuC/6zbsTP8TXJDkBj3GIxqg=": {
            "valueMac": {
              "type": "Buffer",
              "data": "Hh+uyzBwCUjPjAF0YVVz4DGbO0L1ot0DAkn4dGfYGAU="
            }
          },
          "XUYHj+XuMrS8yTusLJA9qOnHO6Ks6Enh+A0XP1wf+9c=": {
            "valueMac": {
              "type": "Buffer",
              "data": "r3bqsxmzfWo+C4wSSnLsO6KxaASGA7nR3yv4De217L0="
            }
          },
          "bd8vvzzJkQvuZPULj0p0egVh/nIGIYuVE0ZxBDa/JsU=": {
            "valueMac": {
              "type": "Buffer",
              "data": "NPsuWK8QdeGOc7OXEhzLzI1LS4aLg04lfMsqZnu31EQ="
            }
          },
          "Z5aCT2u5RLeirLdNe9weUk/nopvId+wHHKxwOiCsNeA=": {
            "valueMac": {
              "type": "Buffer",
              "data": "DRI61TOsF6q4THD78n+bJb6XFNfGIbWzwaw7mO1nOh4="
            }
          },
          "PM2W2ik81acSy+67VccIcvYrB6xPeLt8MxDdIh5zSEA=": {
            "valueMac": {
              "type": "Buffer",
              "data": "aUt4M2x99pTv27VbFonKKRBfMbQWhBdj6R40t6SA/UU="
            }
          },
          "/uzA7SXTvt1j2Dg5PNp1Oc/4GtXlTW7g7IzghnhJ1z8=": {
            "valueMac": {
              "type": "Buffer",
              "data": "dVzd945YhOBWfLyOQPKWheoJbTyJ+rzAV21Uh8AD2fM="
            }
          },
          "UBVtbp+ekIat6O7vvEaMC3i6lpxT1GPxWY2tuEObmAc=": {
            "valueMac": {
              "type": "Buffer",
              "data": "7s+o7x2aRmoraMjFmi22ASgj8/LPo1d3kTkOqvgHAQU="
            }
          },
          "vTBCVG/4pXfhng/MM5EBaDuJTNRH1A/iH/PIN6N7TUY=": {
            "valueMac": {
              "type": "Buffer",
              "data": "huEb0gW1S9LLc/CWn8oXpbtyqyREQPrpvKfW3d7c2fA="
            }
          },
          "sRh3RHaMwPOVJEJKslk9NORfn549A7xBMCSAGd/NH34=": {
            "valueMac": {
              "type": "Buffer",
              "data": "500wd1rVc1jFgPwJuh0QbGrutkFA6GA3hln5lqEdzmg="
            }
          },
          "ft1vwBmVZ9s2bh32gmjsY/G0UMAExowjodMMSginUO4=": {
            "valueMac": {
              "type": "Buffer",
              "data": "/OT1kQO+dzmaTZy2KdSyqRkpSW4MdeCaTjdAFYdZo54="
            }
          },
          "K82OnYjpaCGeDOiFsdlj1RhStV1EYHQX0g7GrFwNw40=": {
            "valueMac": {
              "type": "Buffer",
              "data": "pGKFUXEED5L4C0sym+MnkFwdr4vqvY3PsB14IPBWQ4I="
            }
          },
          "z2HxGUeCjienC5gatS3N684FfzmdgOQSa1uvrdLj2Cs=": {
            "valueMac": {
              "type": "Buffer",
              "data": "zfKkOTUbI7T2Be+FPR9VkJOIqocUz0R4U871PjJETAw="
            }
          },
          "CrVNBcX3nt2OMlHCtSatxXkUWctyEfygslMzLwxCr/0=": {
            "valueMac": {
              "type": "Buffer",
              "data": "+Oh5tHB9gDJ/LHHd+DO6xg62NSJnvSesJcrQWW8Uhuk="
            }
          },
          "vb8lM3J1GUemdpJtDQJq8OZ63OWaFSPd/o3fOTFZ6qA=": {
            "valueMac": {
              "type": "Buffer",
              "data": "0o9/v860xUxVlNrljcrfpnmvuy+rcx9aOffHcF1NH7I="
            }
          },
          "3hBtRDSMPDavTuW9aIyZZDzwcwgv90SbLHBZrCxbttw=": {
            "valueMac": {
              "type": "Buffer",
              "data": "KwlrY6va4PSsIdGWxFI5TKWXbz0J3Io3eaHGAgP1sFg="
            }
          },
          "4uW6IYd699rZ5NISl3xYNV8AJZs32+Ys7PWWuDIqjKI=": {
            "valueMac": {
              "type": "Buffer",
              "data": "Bc0uz/6hETj4IzHs/sQ5JkgA1Q6F0O4RVkzydWm7hDQ="
            }
          },
          "PTbpKw1CvvWf8v96wgNVhxl56couD6l2tGDPRuriZig=": {
            "valueMac": {
              "type": "Buffer",
              "data": "Y2aHyi8ITrokNIkxVZ7Mq8XPml3H4zEvraZogQ9gur4="
            }
          },
          "1ZJLGrnoW+uL2d2VCW0CwDeC6GgzpsXBopgrWcH3dlo=": {
            "valueMac": {
              "type": "Buffer",
              "data": "YT9TuOUyvBjlJYTibG7qI5vCj1eilNRwjN3a9PL1+XE="
            }
          },
          "WXj+1r8/A1vMPJf9gEHvoK55WuidVAtXkhLg6cKZiCQ=": {
            "valueMac": {
              "type": "Buffer",
              "data": "y45EmvN5kBK9i38kTEQoX6wtCj+jEzfVSFhPlM/W/T8="
            }
          },
          "eNUwLMv6iuO2vXyoDzY0IJ27dDosM+Qyrzu8t35KfmM=": {
            "valueMac": {
              "type": "Buffer",
              "data": "YaQU0hA43PBu9rhW4Oi5Uh3VDKLbLoN/bQZoRpLZDU8="
            }
          },
          "mSFz9Z8sMsjjtD9r+tvYanmQLfnRNj00Tb6LaoDHfvw=": {
            "valueMac": {
              "type": "Buffer",
              "data": "joBLSygzSXnfui9C/rGjCzA6sm6pazTwPrdJCcoZsJQ="
            }
          },
          "inxBZTTAiVvOb/f/EBJkk8GIorKduAJgwpAB+llIcX0=": {
            "valueMac": {
              "type": "Buffer",
              "data": "C8XIUN0zthNoxQ5EESmym19qDahkcV3zRg9GtelrNfs="
            }
          },
          "kpZ+e30ORRohnWAQR1UQp8Cwl5CxbYrmMdIbAyvv+vU=": {
            "valueMac": {
              "type": "Buffer",
              "data": "QipuZsqpG3yOZ0ZB0sdMRKPfIJdtgUHpYyPpW4MDeLM="
            }
          },
          "zsnv4l5S3dcNguh1orKGnyq8vLxi0KbK/inVqw7T6qw=": {
            "valueMac": {
              "type": "Buffer",
              "data": "9EUZMQfp4WrYOFCG7LNgBtxJfLEDsC8jFQm5DWo9PZY="
            }
          },
          "qBOCf3QE2apTtubykAR0Ju2z0D45434Gxe0QueM4Y+E=": {
            "valueMac": {
              "type": "Buffer",
              "data": "wkfPnRcV7DsYTonaf0mAhaVBRmFTxavk28HHkyg/OCU="
            }
          },
          "Bz9C7VJ1VURJ1ucDqUjA8S8AaKjKm/0fUBzjWKjpJdI=": {
            "valueMac": {
              "type": "Buffer",
              "data": "kbjkGto9FNricrsvn2uY1F/VNTeHAw6rQwP8MLe6igc="
            }
          },
          "7sU0bQTtzOlqRK7k6yMly3mgrrJHPBMj8sXlXqpxHxA=": {
            "valueMac": {
              "type": "Buffer",
              "data": "4IGkLApkwlUJCBxy/VIjze4j74Q2p8xbfLiyVGtADH4="
            }
          },
          "a6fVNAKVx2RrrwQC1rXPKpHZGxTx9tx+1/S/uQEvqP4=": {
            "valueMac": {
              "type": "Buffer",
              "data": "Is9KF2I47DgF9W1F+DXjaL3RbRDCdoC6EpXQmDou35g="
            }
          },
          "BeXg5DHHf9OkONWkeyWkW89A1FawoUvB7ZY60IBiUtc=": {
            "valueMac": {
              "type": "Buffer",
              "data": "iEHVLYj8pDGk3o6Q9TmcbncSufZdvKB/wptrS7CufMw="
            }
          },
          "IjThj2bKU6vzUhYogvU5qkpDo7JkkAxLwSRhZuf7jZo=": {
            "valueMac": {
              "type": "Buffer",
              "data": "iYKFsVDls8lk2C9nnigMvRJmpql0R86AQEXGlEVTosk="
            }
          },
          "0YJ1QBGKY8+5Rer3wqGdMl6Mr1djDzvdi23gQcXFT1U=": {
            "valueMac": {
              "type": "Buffer",
              "data": "XlPEtEXOD6eEMoTlNTLkKMS/VDs6Le5/3y1x5WDj2YY="
            }
          },
          "HR+Zay3yId57vyTCIdRbGml1nRdiFngfIKzCIpl2jXA=": {
            "valueMac": {
              "type": "Buffer",
              "data": "6JZPEHp0CxNLK3TkrYzqHv84NAQ7Hk3AwxZlGl5+s5c="
            }
          },
          "86XPmk10Ag5cXXRHw7fPCJ9Knm0N/mSupkOXrSEvgd0=": {
            "valueMac": {
              "type": "Buffer",
              "data": "mPH7PsKDKc8KTQh4Pr3UrotSlx1vSe9fVChGhE4n5oc="
            }
          },
          "0Vevur3CqSLofxvn+2PuCfYvkqGstIclvR3KmCLTRg8=": {
            "valueMac": {
              "type": "Buffer",
              "data": "usgDEf5oecsF7WC4Xa/gq5aWG7bMbEckD6OqHqQIhGE="
            }
          },
          "jZ6xiUtpgEZZedxmKSNPr13Xn4Vb9IX4GVhZCI+noMk=": {
            "valueMac": {
              "type": "Buffer",
              "data": "mL2tDiAuiKPt19ANRTU5j7yVP6xNBYpAn51J91S7FeU="
            }
          },
          "TOWAjpAojC8bSHS8ZTMGbVBU6dxD7miN/B5YJRCCj1o=": {
            "valueMac": {
              "type": "Buffer",
              "data": "VUcVpxTWB8Yh8PUplPpx7jzRr9EyW6BC0e5gH4kUhlU="
            }
          },
          "FrZ+WqSwGLew+zzv94npkEAz2W+Ok3ARQzNII4Vtdw8=": {
            "valueMac": {
              "type": "Buffer",
              "data": "xqHQN/oa70osPGKw0N2ASUEWdRaPUIErUrWp2rvCTiU="
            }
          },
          "iHWxMbZMsfdneSVKmqAaj0P+Wg8A8HCPVaKCuMde0JM=": {
            "valueMac": {
              "type": "Buffer",
              "data": "+Xn4UDNiQwTYlpWiz7laKCiLnRoSJwdwRxLnqyA8tRk="
            }
          },
          "ligsgkLX+Y9URU7Pj1tMfBju48dX1MrjEIeqMkEHs2Q=": {
            "valueMac": {
              "type": "Buffer",
              "data": "M95t4VjyKKZZtgWiv/z4MWl706sd6VnZ1Z55LE37T9M="
            }
          },
          "HxBt+sywE03NWsmC0pBKhEiO0SCbT9vtbsE1JDeOsaU=": {
            "valueMac": {
              "type": "Buffer",
              "data": "ao/cdRQY7Yci9i4zISNYYPlQI57pM2AlPWLXZONp1L0="
            }
          },
          "6dFl+Cn6sCyQNYAbcntxSPyDb2gu2v0Q8txt+gECuNA=": {
            "valueMac": {
              "type": "Buffer",
              "data": "vehPP1aINsiVGhaE4RobeIzUI6R5SA4tQwSF7Ngcyvo="
            }
          },
          "Aj4BMEFRbGAUcIZaL2FkLInG8o84frlrcUcEbnmdF9c=": {
            "valueMac": {
              "type": "Buffer",
              "data": "SOyGy4IgxM0GIEtJYvBTLJvF4t12FjRnH2nNny7wGRg="
            }
          },
          "94J2V6uLH/zn1k6AgM+SKOBTUTHP4R/nvhpUp3BwWWw=": {
            "valueMac": {
              "type": "Buffer",
              "data": "7USrirJ03qljtbPvYZpw9qdQJpRg790jkynt6+/ezqQ="
            }
          },
          "0M/GfLwn+sUo6mVwMpde+2aIJXr2ob4RlgBD+1wtkks=": {
            "valueMac": {
              "type": "Buffer",
              "data": "YdgYqUqKpxvRIgr+/gnfI3pbu5WZu9Y8kr75zJp5rrg="
            }
          },
          "8mOxOFh4RzRPzVHZIJRGMzXaRIjLrelXhTdTOLfnM7g=": {
            "valueMac": {
              "type": "Buffer",
              "data": "Aes6x9GxOgu/msTIjbdJO8CRGKNRr3UEJPFqBUOu/nQ="
            }
          },
          "zL3TR8zHPCCp+N9L8x+Whdt5JI4YUdrSYHFE347KUY4=": {
            "valueMac": {
              "type": "Buffer",
              "data": "0VkoooTlqO+gmwTkYbmHjmu0Udy7FhlFHxRd7ApMHMk="
            }
          },
          "9fehFIAmDFTDmDKXJxL0RZ1USE38MPLdtVc6PJicr78=": {
            "valueMac": {
              "type": "Buffer",
              "data": "rnyZ4dGo/TS/xt1xwpT/XtntpB4wgXai/TkJGFmqKwE="
            }
          },
          "knckVPXKEeQwXrI6tyGTcFfIX+Yrvc+FZMaQl7ezsxE=": {
            "valueMac": {
              "type": "Buffer",
              "data": "0+EOuiUHDGGfzM7z6iNBDil9LjlY1d4XibO13ajzaFI="
            }
          },
          "VjFXvIISxqisNnK2ogRBqlp+cpMcZ5eP1nIVkFv2WOI=": {
            "valueMac": {
              "type": "Buffer",
              "data": "fEKSolpJ8ilRwUeqaOJaj9NGeM3G0NZZuQCW6cePIys="
            }
          },
          "L7EX7gutXPAxZnYf/rZnvD4oSOu5v3iWc33u8B7lpcE=": {
            "valueMac": {
              "type": "Buffer",
              "data": "nL/yahNzqbMpbz6aqVh/sWEm+9fglirG1HmOD7COyIo="
            }
          },
          "awRFKLDTYJeVRkirv8l6kVVmu8dgkMe/SN2j3dlNVc8=": {
            "valueMac": {
              "type": "Buffer",
              "data": "3HmvQTDlPyKjY3FRdXf8/Zg02y4QsLMRbZbuR3u59JA="
            }
          },
          "0WLteLwdiFfZ8BFHWeNWSfUIDNdCgFv8lThmYAVKw6Y=": {
            "valueMac": {
              "type": "Buffer",
              "data": "u2t64CjkweBqjlE8yF6s8JspAvZ9OPI4c21oXl6KjwM="
            }
          },
          "jBa4YcsFf5p4iwHDvZA82/5/9MoR+LLGRKIFdN9QGP4=": {
            "valueMac": {
              "type": "Buffer",
              "data": "Er7+GjyWtnkQDwnDG24Y0VGuVBkJscqzXG1TjWD9AGs="
            }
          },
          "1N6xtrvhP7Pby9UBTY8dIezGoz172XWkz2zn1eJdbiE=": {
            "valueMac": {
              "type": "Buffer",
              "data": "t955Hsofi6k/8JwsToBA5fJqzC5zItlOBcGWnMi8G+Q="
            }
          },
          "FMLYjLvQ3Z4b6N0GpmIpTljfYKnNWkqX9ZKCeSPEvt0=": {
            "valueMac": {
              "type": "Buffer",
              "data": "VKkUwjruansxbI/6J+Bb15rHe9xdLshH0ywlf6ReH3w="
            }
          },
          "+9Fz9hvbTopnr2HlWYBL/RvZ/SbKZaphI3Aagh+jXMQ=": {
            "valueMac": {
              "type": "Buffer",
              "data": "V967AOC4mZ8EfbIQGynRwQF4xvjEWkprI7fBXPFeGpM="
            }
          },
          "ra28d5IW2sBinZx2JKwHbgNwZrdlvo/pRFnc/S/8zgE=": {
            "valueMac": {
              "type": "Buffer",
              "data": "LvRXRPO389z+cH9cpjDY5rQO8eAIaNjwg/rAR5h6iTM="
            }
          },
          "vWMf4ca75d6p8MLZl0J0sF6ibJzo0+DvlFfmTe/ACEU=": {
            "valueMac": {
              "type": "Buffer",
              "data": "/qpqyyVlhXJEEU5ON0lfpBS5D1Y/Eo8qdN1IZDElKkI="
            }
          },
          "Izh1q5ti4l6rFmXv5nKBlFwKa9C8v5+YXZ1d2kw0hr8=": {
            "valueMac": {
              "type": "Buffer",
              "data": "0hkByu9kW8TjQyEFROTsS/FRWQLy1TgB6fXoPv9b6qE="
            }
          },
          "MFl8cTLtfNoUrWD0bJoCUMMgDejmmGmpTRseEZAhzxQ=": {
            "valueMac": {
              "type": "Buffer",
              "data": "6T+tVRFwpC7Ri6Tp/pnTV2FehGhsTNKSCGOk3BGwkWQ="
            }
          },
          "+4NvN1nJVsBSszFnVEdhts6jbzbqqzVlBinYEBhPl1U=": {
            "valueMac": {
              "type": "Buffer",
              "data": "43Ng86Btsk6QZXWcMfGqkzp2UlDCCO/sq6c0pnyc/hA="
            }
          },
          "XHfvgsULVYLVhiEHNWSTM1kN2g58U5oPrS2sj1Whw64=": {
            "valueMac": {
              "type": "Buffer",
              "data": "u1u4rhqUlRWf6nXIZNoWirHKo+CZqL/twArivz7TpAo="
            }
          },
          "0wYYEOSFEKpqb0uM4JbL+eE0vj1Ow2dKvBrZsiyW9sE=": {
            "valueMac": {
              "type": "Buffer",
              "data": "LBjJLKbz/9tJbgbK4nPOel3xQyFX+lyO4rdiK6p9Bnk="
            }
          },
          "Njn1aT8KUfHcSUH0h+kum3dKY2Usn21y/vUgAiylDgI=": {
            "valueMac": {
              "type": "Buffer",
              "data": "jzyPA6F5M0bQXJ6M/nVPqOF3PSJfB/RCjnXgJuhIrwQ="
            }
          },
          "qxPr83gU1Z6DFon+diXfoDv5H+kg5zJBtGXkLCT+mB8=": {
            "valueMac": {
              "type": "Buffer",
              "data": "DAq6laLo6xSNhAVjsvK67azXMy04PHpVUTUWbdMXHJU="
            }
          },
          "GEPX6JgcPH8Vv6j7dgdbTHpSxrtRcsQKhNF28c27y6E=": {
            "valueMac": {
              "type": "Buffer",
              "data": "PZ4oQyk1/S1naBVcW7YLisAAhhZfu5x1zpgxIaW54vE="
            }
          },
          "PrfJZ7IoFRUM/El35x/9yQ20Jo76voXrrtijG1mZaoc=": {
            "valueMac": {
              "type": "Buffer",
              "data": "dj9zDtWR3sRDdEZ+n45MrMS6eOuiAQaFd7rYSbu6kjk="
            }
          },
          "rseoRP8h3HEoRO7yHUg4mVk1T1HeiqmBL2+fS9WMI20=": {
            "valueMac": {
              "type": "Buffer",
              "data": "HtYloDnQ/8xo1/hH5F8KzceigVGdxY9f5rsNUfie9zE="
            }
          },
          "ZqkNc7ftS1JlwC9KvTSwCYOfdo67bTdIeFI14ItBhZg=": {
            "valueMac": {
              "type": "Buffer",
              "data": "nT5+j/mBstbM8uHH37lZkjXlQdJrLqpWM0Xuwy6QkOI="
            }
          },
          "o0Ozcbdp/k6F6Rgg0/OHsIN/j/TR3HuIJLLZIvUa6SY=": {
            "valueMac": {
              "type": "Buffer",
              "data": "b49AKTs0PVVJgODSU5w+mbrNB7pM0pSKpROB+wEduFs="
            }
          },
          "wlOZ5XVvSZIQjjhs4mzqKyk1DmuDlJc9Ir+ig8M2Pmo=": {
            "valueMac": {
              "type": "Buffer",
              "data": "3szDXyZRFKsQOe8v3F/vC3nNmTrkdjUTU1YEc4LBneE="
            }
          },
          "3S2URrx9n2X6NdrjzZbYiCwqOuZ5ftuWvWf8cubD5+Q=": {
            "valueMac": {
              "type": "Buffer",
              "data": "Grf1oO0oU2j609Qv7gdUqBGQYIHBsMUd/85zSZC0xek="
            }
          },
          "ixTNe5iwRP03UMHWhHx3QxlKQHJEHbZOEi3XXCz3hO8=": {
            "valueMac": {
              "type": "Buffer",
              "data": "5203eqtzC0fNXxyzwTuipmjKQ2za8xQo68rMGuL5fVU="
            }
          },
          "9PYtEubygSLYCVlP3/h+c10ajNv6bPxCgKs5WcobbmQ=": {
            "valueMac": {
              "type": "Buffer",
              "data": "MOyLgu4wzyxnPGqlp9SW05egs+jv7zkWEOy7IpsB3Yw="
            }
          },
          "dCC98bNBlsJmBtrQj5+n8hIEETxRKRPHc9ae5K2e2kQ=": {
            "valueMac": {
              "type": "Buffer",
              "data": "TLZtqABef11HhGTejOoNJNfOZp6LwFVb95xyq7GzLU4="
            }
          },
          "kQxk/fdiKWvUTC6Tt8XawtB6+L6rYNplJK08CgIoblc=": {
            "valueMac": {
              "type": "Buffer",
              "data": "YpTLarEmltsKILjFYe4SAPpzetWRGA/fcF9eFC9H96g="
            }
          },
          "NOt1iHIeun+RzTX9Nj1gPl3i10zX0sD4ZAShr6kmUZc=": {
            "valueMac": {
              "type": "Buffer",
              "data": "3bzSWO1B6kPca0DNZiUiKDaak5PPzEgQ7F9E/KDpDzQ="
            }
          },
          "FvYLCKmAhtKz3fPihOkTVuxP8fcNa5EFBVUIlhySwgI=": {
            "valueMac": {
              "type": "Buffer",
              "data": "RwX3GPPjq307bZioRtewacYAWshM659WlC5rQ4dPqXc="
            }
          },
          "bbOFMCYkY5vdBqEzJDd/j/ll86gcY96t0kf65MVuxW8=": {
            "valueMac": {
              "type": "Buffer",
              "data": "n95gCVnSts/XdBVBSiVXostDDq/JjrZ9+gTc8bNJljs="
            }
          },
          "o042W0BJKzDlx2mqokCp2Y2tM4qMV0a1AR4AASAybqU=": {
            "valueMac": {
              "type": "Buffer",
              "data": "U3iJZGP3lnqchfawsfu1eqVfN4yPLVORYvCVVUYN0Jw="
            }
          },
          "qAXAOLDEmZGVJIUqHFZfhd5qETzKsl+RISraNfAEku0=": {
            "valueMac": {
              "type": "Buffer",
              "data": "xjgx6ObIVcu0A7BUVvMRBCOdifw0t66pxUfT8DwUSMg="
            }
          },
          "D18LkI2V0AeEEVG/C5NfwMxs/LDMy92e/ofS5bepLDw=": {
            "valueMac": {
              "type": "Buffer",
              "data": "tP1I9dd9Mhz/v+NulBbVE8D74Cbjp5ZzwCyCUpWxi/Q="
            }
          },
          "qbPNFXNZvQowWvSZjB1thtISq+ju0dayVg+hQyDB4Zg=": {
            "valueMac": {
              "type": "Buffer",
              "data": "KXIIHZpzZ2+Kn+lm90X7f20MG3ipaQZwvsLnVHCXv4k="
            }
          },
          "Yb86PengSm120K4bsWflyeOMdpI7YXSBAUswZhx9Chk=": {
            "valueMac": {
              "type": "Buffer",
              "data": "PUkGmLd6qL0o8MoW0liQ2miXOzPzmQn8ZjSwLTZ6V4A="
            }
          },
          "ghd8giPpSGGyDzeIKipB18eanWnXPDrAVtf71ViqlpU=": {
            "valueMac": {
              "type": "Buffer",
              "data": "/P5fcJOhArno3EHjzX4sD7FVKIB2Wiw1SjTY4FXSpQI="
            }
          },
          "33ye1Kigh7Iy/mPG5XpWrYp4TuXae0fhGScOrh+fbrU=": {
            "valueMac": {
              "type": "Buffer",
              "data": "4fPnURA8wBFZPqbucTfLbCR3DkwTORLeorNsaxA729o="
            }
          },
          "bxXv3mOn21Fw0SYbZfDMkUoQTHLuO+ZGZHl/nmTNuO8=": {
            "valueMac": {
              "type": "Buffer",
              "data": "wf4U+rlqQ66H+7vUPT77tiz/SGMoWFJo5WrEgnNo3Bg="
            }
          },
          "QkLW4IUb7EG7tz9QsQ18yXflHCJed4u+70lQRAf3Mr4=": {
            "valueMac": {
              "type": "Buffer",
              "data": "Jc6kfEfbPjZE7WLkiXCVC9zDug295wZb/3pAKmwVIzA="
            }
          },
          "40Qzti6X5BDvqEnSUk/f4z/PueBHOBbgxVGSawY9iKU=": {
            "valueMac": {
              "type": "Buffer",
              "data": "bFI4MnNaj2Ja3N28bfXFthjou/uC0ZkY8BDDVmtWCNo="
            }
          },
          "C8lU3jC0yBbkCQWmwfSnsYtjaZUSNFyLe2dbW7Hhrw4=": {
            "valueMac": {
              "type": "Buffer",
              "data": "DDokcZeJSBEDMLpvKIUjy94vLe2E749hDIqkABxJmcw="
            }
          },
          "DGTSOPAdcl2/LYcuJE9rdick8gFC56BqGxwtt6I6MAc=": {
            "valueMac": {
              "type": "Buffer",
              "data": "4FH4CS8oTOH79gOYV84TbgqJa9Jk/szpUV5PKtv6Sh4="
            }
          },
          "Tludv78TmOJwaAgdxHErIY4Lh1ZdmY0/SdTx96eiI9Y=": {
            "valueMac": {
              "type": "Buffer",
              "data": "D0dl68HFp6aolZ+n4O6fHscQJUum1M8bk2ftoVGBjmA="
            }
          },
          "x5fIF42Xk/5ap7q3Bc9jaZ62lO5HFlzYAiBsho6KEGw=": {
            "valueMac": {
              "type": "Buffer",
              "data": "kHfIlGgmzgYZiTGhmCOOqexRZrADSM0oUjMGjfEBn4Q="
            }
          },
          "gkxBcbLJxEFYf1LB9ryQu8eaYhZKiiTnxwxBmvNaz7Q=": {
            "valueMac": {
              "type": "Buffer",
              "data": "lk92WUPRZQMjjsT4T6wmKXtm37e/iOsvIrP1eQhqrjY="
            }
          },
          "BPibtP5kBs2yBuR9DNy2Ng7NZZI96o2eZms2onj72mI=": {
            "valueMac": {
              "type": "Buffer",
              "data": "3/W36au1vnUy8WVz6RkwWUaOQ1UAA6qP7k3w5FLnlTc="
            }
          },
          "b0xNj5XPlBpNvgTgq3wUnsJ5BuPjq1V2mqRg9yAe2z0=": {
            "valueMac": {
              "type": "Buffer",
              "data": "IctMAmgypXl2KYD/ZKkz7zG3VuDiCVZjs3ywBtvfSaU="
            }
          },
          "GPQpKHCU7jK/ba53Nd9tKk2iq8ufjJ476kUnPg3YYV0=": {
            "valueMac": {
              "type": "Buffer",
              "data": "Lcio6IhBdsLk+V5wldVM43sZ1psfj0o43r+fxB4Y2IE="
            }
          },
          "e/bCns30d8ww+o6GgakZCVxYQFFeRfPBMt8TotiaipI=": {
            "valueMac": {
              "type": "Buffer",
              "data": "RkyxDRo4PcGnElew8se5vknJUIXmnrCmCo7+pSMB+x4="
            }
          },
          "4ToG+38PLtxkCLibnuXS6Q5lCOiIA9zHVIsn6Zd53yE=": {
            "valueMac": {
              "type": "Buffer",
              "data": "cN9NvLijzc0gSPTWzWQ+vUOoEXfmp8pVB0sWlF8sQrU="
            }
          },
          "67IvyUncZd2Sl6ucVHZ3P1wGbJUiivnQ3Sn+U05gJfg=": {
            "valueMac": {
              "type": "Buffer",
              "data": "jtc0UtF9Zo8F+s37v51zbkSwUgNnUBovM17o+SNa2xg="
            }
          },
          "nHZ8wrJSArpnThxPE/k2uGhwWECOxYLopa+ACPXz3qU=": {
            "valueMac": {
              "type": "Buffer",
              "data": "fVyj5Aa4MPt25i/86gb66uvvTXJpIv38glenxG/kMSs="
            }
          },
          "s30afEO8kCfaYx5vxk/3UCCiIT9yEnPX0LBnOCrtays=": {
            "valueMac": {
              "type": "Buffer",
              "data": "CTN0TUuH79uqp/SkRjBazsdDEVFlXU5U4YPiRKANuQU="
            }
          },
          "m9werAkpvghk/CNb799bLytpVPwajZFBU0f4QSXMxcU=": {
            "valueMac": {
              "type": "Buffer",
              "data": "C6m9BOSGy0oSmD6lV++20WE0pNjkujiugS2pUFjHlN8="
            }
          },
          "S95f68X14aSeTh7PqBnIS3scwyoCXw6rMqZdPIFvyj4=": {
            "valueMac": {
              "type": "Buffer",
              "data": "66/QOMc8JHEiLkWQRHHxEmvAWwpboPw2yQmQDOpSRNc="
            }
          },
          "+PELYO7a9s2R8eWhtlCU8N0KXNeQr+Q1d5e21xahFT0=": {
            "valueMac": {
              "type": "Buffer",
              "data": "Bi3/dW2u+rCXU4VYa0sx83dHhlL8Ke1g5f3AhL6lxIo="
            }
          },
          "P37leouOaFweTghQB1tvx/p+d/XMPHtKyOmucr+ceJ8=": {
            "valueMac": {
              "type": "Buffer",
              "data": "ga1Fdn0gYhaAE1DfHIoWAKPvggCb/q6ZsrTuV4fjQ2I="
            }
          },
          "3T8lHNZfVD5LJlvsCzbjD3Geawq/8//MA2Mqj5Erwfo=": {
            "valueMac": {
              "type": "Buffer",
              "data": "pute7qmX6s9b+7GtoMypMsrj3F5JTTCH7VJkkT87WhA="
            }
          },
          "+GkvWyVYD22RVC6AwTEAApMgTnu74Jc7LVHjXlBOJS4=": {
            "valueMac": {
              "type": "Buffer",
              "data": "mc7E1B3GTIfP54RTu9IbbrmmglTmgc+4R8jZja517WU="
            }
          }
        }
      },
      "regular_high": {
        "version": 1,
        "hash": {
          "type": "Buffer",
          "data": "DiZsAE0TNzo+lqZ3G36E6eun0kgvGKFCmM26axlvBXbboTG1BMyyBf8Ybsz1fF9scSpHvmtAKbJrP0nua6+Yars8PHkjfnGqpdHBE5SMaJ3YKfHExNhBMQYM/903ebS7UvWjR/qsAnqjcJ4BR41bEXT15eGyjtx3D8D+P8uFQiA="
        },
        "indexValueMap": {
          "mGeQlhVx+ItsxcQN9D0vJK+4ATge/j6fZCBXLf1rpiY=": {
            "valueMac": {
              "type": "Buffer",
              "data": "3KilMqvN9hyeoedTUnna3zd4LH1JyZ8sT6zWvJzJm9E="
            }
          }
        }
      },
      "regular_low": {
        "version": 1,
        "hash": {
          "type": "Buffer",
          "data": "0/L9foJcvM0bX3fXBUI1HTPKnUGU2eu+ot7h+MRQaTcTX8xFhdl5QNmtPDDSat8iewg1Dq6tCpM6sU12Fpyhnzbkor10gUfQx/w59FMqetaurSdzf1O/AUUcBhYdndP9xBxm9ZhufKExSpb//I+x724i4oGHjbPbRTxa3rrrzbk="
        },
        "indexValueMap": {
          "4mPg8pBnB9WbL2ah4IR5X77yDfQ6JtpcQDDC1+K6AUI=": {
            "valueMac": {
              "type": "Buffer",
              "data": "vKw/RNwcTzcqA6LViqUXgvXHjhks35WmAgqJNd+6enA="
            }
          },
          "2PFD8iLfJNIoxCG+AAdUtgjqdrF3thCaBUrAAZxTkPg=": {
            "valueMac": {
              "type": "Buffer",
              "data": "SV90+HUnjFgA90ExL1C57D6NdRG4F3ev/OjwudhNrB0="
            }
          },
          "332zqm/eW9H0OGs7JXxE4/N7C9USyBRTpnXOmt7dPLo=": {
            "valueMac": {
              "type": "Buffer",
              "data": "wTYnSv/R8JaR3DrhKoynIZRhJNKz1ChrMx1gMcgY1xc="
            }
          },
          "XeBt+tcx9j094YJcG09I4qj97oyKcqNJBk0Xj7abx4M=": {
            "valueMac": {
              "type": "Buffer",
              "data": "jnQdgMW2Af/nyvlj1+y5w6SAdq/jYNopoB1435rZQy8="
            }
          },
          "Vk1jngtDkZji+Re6RbMTJd9KkjdVRfzomvj6flZlqfo=": {
            "valueMac": {
              "type": "Buffer",
              "data": "9KbbI9rJnhbCN8JzWcryrGAP42zbDuuI9InhKr7bnXY="
            }
          }
        }
      }
    }
  }
}